python_skeleton_project/__init__.py
python_skeleton_project/greet_world.py
python_skeleton_project/version.py
python_skeleton_project/tools/__init__.py
python_skeleton_project/tools/hello_world.py
python_skeleton_project-0.5.data/data/share/python_skeleton_project/README.rst
python_skeleton_project-0.5.dist-info/METADATA
python_skeleton_project-0.5.dist-info/RECORD
python_skeleton_project-0.5.dist-info/WHEEL
python_skeleton_project-0.5.dist-info/entry_points.txt
python_skeleton_project-0.5.dist-info/top_level.txt
